gradient_swarm_optimization-0.1.1.dist-info/licenses/LICENSE
gso/__init__.py
gso/core.py
gso/exceptions.py
gso/utils.py
gso/validators.py
gradient_swarm_optimization-0.1.1.dist-info/METADATA
gradient_swarm_optimization-0.1.1.dist-info/WHEEL
gradient_swarm_optimization-0.1.1.dist-info/top_level.txt
gradient_swarm_optimization-0.1.1.dist-info/RECORD
