Metadata-Version: 2.4
Name: gradient-swarm-optimization
Version: 0.1.1
Summary: A Python implementation of Gradient-guided Swarm Optimization algorithm
Author-email: Emrullah Gazioglu <emrullahgazioglu@gmail.com>
Project-URL: Homepage, https://github.com/gazioglue/gso
Project-URL: Documentation, https://github.com/gazioglue/gso#readme
Project-URL: Repository, https://github.com/gazioglue/gso.git
Project-URL: Changelog, https://github.com/gazioglue/gso/blob/main/CHANGELOG.md
Project-URL: Usage, https://github.com/gazioglue/gso/blob/main/USAGE.md
Keywords: optimization,swarm intelligence,metaheuristic,binary optimization,gradient-guided optimization
Classifier: Development Status :: 4 - Beta
Classifier: Intended Audience :: Science/Research
Classifier: License :: OSI Approved :: MIT License
Classifier: Programming Language :: Python :: 3
Classifier: Programming Language :: Python :: 3.8
Classifier: Programming Language :: Python :: 3.9
Classifier: Programming Language :: Python :: 3.10
Classifier: Topic :: Scientific/Engineering :: Artificial Intelligence
Classifier: Topic :: Software Development :: Libraries :: Python Modules
Classifier: Environment :: Console
Requires-Python: >=3.8
License-File: LICENSE
Requires-Dist: numpy>=1.20.0
Dynamic: license-file
